parnas.py
parnas/__init__.py
parnas/cli.py
parnas/logging.py
parnas/options.py
parnas/version.py
parnas/medoids/__init__.py
parnas/medoids/fast_pmedian_finder.py
parnas/medoids/input.py
parnas/medoids/medoid_utils.py
parnas/medoids/pmedian_finder.py
parnas/medoids/pmedian_utils.py
parnas/medoids/tree_coverage.py
parnas/medoids/tree_indexer.py
parnas/medoids/tree_medoids.py
parnas-0.1.7.dist-info/LICENSE
parnas-0.1.7.dist-info/METADATA
parnas-0.1.7.dist-info/WHEEL
parnas-0.1.7.dist-info/entry_points.txt
parnas-0.1.7.dist-info/top_level.txt
parnas-0.1.7.dist-info/RECORD
