Metadata-Version: 2.1
Name: parnas
Version: 0.1.7
Summary: Representative taxon sampling from phylogenetic trees
Home-page: https://github.com/flu-crew/parnas
Author: Alexey Markin, Sanket Wagle, Siddhant Grover
Author-email: alex.markin57@gmail.com
License: MIT
Platform: UNKNOWN
Classifier: Programming Language :: Python :: 3
Classifier: Programming Language :: Python :: 3.7
Classifier: Programming Language :: Python :: 3.8
Classifier: Programming Language :: Python :: 3.9
Classifier: Programming Language :: Python :: 3.10
Classifier: Programming Language :: Python :: 3.11
Classifier: Topic :: Scientific/Engineering :: Bio-Informatics
Classifier: License :: OSI Approved :: MIT License
Classifier: Operating System :: OS Independent
Requires-Dist: numpy (>=1.17)
Requires-Dist: numba (>=0.57.0)
Requires-Dist: biopython (>=1.67)
Requires-Dist: dendropy (>=4.5.0)
Requires-Dist: phylo-treetime (>=0.9.4)
